syncmaster/__init__.py
syncmaster/db/__init__.py
syncmaster/db/factory.py
syncmaster/db/migrations/README
syncmaster/db/migrations/__main__.py
syncmaster/db/migrations/alembic.ini
syncmaster/db/migrations/env.py
syncmaster/db/migrations/script.py.mako
syncmaster/db/migrations/versions/2023-11-23_0001_create_user_table.py
syncmaster/db/migrations/versions/2023-11-23_0002_create_group_table.py
syncmaster/db/migrations/versions/2023-11-23_0003_create_queue_table.py
syncmaster/db/migrations/versions/2023-11-23_0004_create_connection_table.py
syncmaster/db/migrations/versions/2023-11-23_0005_create_user_group_table.py
syncmaster/db/migrations/versions/2023-11-23_0006_create_auth_data_table.py
syncmaster/db/migrations/versions/2023-11-23_0007_create_transfer_table.py
syncmaster/db/migrations/versions/2023-11-23_0008_create_run_table.py
syncmaster/db/migrations/versions/2023-11-23_0009_create_celery_tables.py
syncmaster/db/migrations/versions/2024-10-07_0010_add_pg_trgm_extension.py
syncmaster/db/migrations/versions/2024-11-01_0011_create_apscheduler_table.py
syncmaster/db/migrations/versions/2025-08-10_0012_update_ts.py
syncmaster/db/migrations/versions/__init__.py
syncmaster/db/mixins/__init__.py
syncmaster/db/mixins/resource.py
syncmaster/db/mixins/timestamp.py
syncmaster/db/models/__init__.py
syncmaster/db/models/apscheduler_job.py
syncmaster/db/models/auth_data.py
syncmaster/db/models/base.py
syncmaster/db/models/connection.py
syncmaster/db/models/group.py
syncmaster/db/models/queue.py
syncmaster/db/models/run.py
syncmaster/db/models/transfer.py
syncmaster/db/models/user.py
syncmaster/db/repositories/__init__.py
syncmaster/db/repositories/base.py
syncmaster/db/repositories/connection.py
syncmaster/db/repositories/credentials_repository.py
syncmaster/db/repositories/group.py
syncmaster/db/repositories/queue.py
syncmaster/db/repositories/repository_with_owner.py
syncmaster/db/repositories/run.py
syncmaster/db/repositories/search.py
data_syncmaster-0.3.0.dist-info/METADATA
data_syncmaster-0.3.0.dist-info/WHEEL
data_syncmaster-0.3.0.dist-info/licenses/LICENSE.txt
data_syncmaster-0.3.0.dist-info/RECORD
