Metadata-Version: 2.4
Name: data-syncmaster
Version: 0.3.0
Summary: Syncmaster REST API + Worker
License: Apache-2.0
License-File: LICENSE.txt
Keywords: Syncmaster,REST,API,Worker,Spark,Transfer,ETL
Author: MWS Data Bridge
Author-email: onetools@mts.ru
Requires-Python: >=3.11,<4.0
Classifier: Development Status :: 3 - Alpha
Classifier: Framework :: FastAPI
Classifier: Framework :: Pydantic
Classifier: Framework :: Pydantic :: 2
Classifier: Intended Audience :: Developers
Classifier: License :: OSI Approved :: Apache Software License
Classifier: Operating System :: OS Independent
Classifier: Programming Language :: Python :: 3
Classifier: Programming Language :: Python :: 3.11
Classifier: Programming Language :: Python :: 3.12
Classifier: Programming Language :: Python :: 3.13
Classifier: Programming Language :: Python :: 3.14
Classifier: Programming Language :: Python :: 3 :: Only
Classifier: Topic :: Software Development :: Libraries
Classifier: Topic :: Software Development :: Libraries :: Python Modules
Classifier: Typing :: Typed
Provides-Extra: scheduler
Provides-Extra: server
Provides-Extra: worker
Requires-Dist: alembic (>=1.17.1,<2.0.0) ; extra == "server"
Requires-Dist: apscheduler (>=3.11.1,<4.0.0) ; extra == "scheduler"
Requires-Dist: asgi-correlation-id (>=4.3.4,<5.0.0)
Requires-Dist: asyncpg (>=0.30,<0.32) ; extra == "server" or extra == "scheduler"
Requires-Dist: celery (>=5.5.3,<6.0.0)
Requires-Dist: coloredlogs (>=15.0.1,<16.0.0)
Requires-Dist: fastapi (>=0.124.0,<0.125.0) ; extra == "server"
Requires-Dist: horizon-hwm-store (>=1.1.4,<2.0.0) ; extra == "worker"
Requires-Dist: itsdangerous (>=2.2.0,<3.0.0) ; extra == "server"
Requires-Dist: jinja2 (>=3.1.6,<4.0.0) ; extra == "server" or extra == "worker"
Requires-Dist: onetl[all] (>=0.15.0,<0.16.0) ; extra == "worker"
Requires-Dist: psycopg2-binary (>=2.9.11,<3.0.0) ; extra == "server" or extra == "worker"
Requires-Dist: pydantic (>=2.12.4,<3.0.0)
Requires-Dist: pydantic-settings (>=2.12.0,<3.0.0)
Requires-Dist: pydantic-settings-logging (>=0.1.1,<0.2.0)
Requires-Dist: pyjwt (>=2.10.1,<3.0.0) ; extra == "server"
Requires-Dist: pyspark (<4.0.0) ; extra == "worker"
Requires-Dist: python-json-logger (>=4.0.0,<5.0.0)
Requires-Dist: python-keycloak (>=5.8.1,<6.0.0) ; extra == "server"
Requires-Dist: python-multipart (>=0.0.20,<0.0.21) ; extra == "server"
Requires-Dist: pyyaml (>=6.0.3,<7.0.0) ; extra == "server"
Requires-Dist: sqlalchemy (>=2.0.44,<3.0.0)
Requires-Dist: sqlalchemy-utils (>=0.42.0,<0.43.0)
Requires-Dist: starlette-exporter (>=0.23.0,<0.24.0) ; extra == "server"
Requires-Dist: uuid6 (>=2025.0.1,<2026.0.0)
Requires-Dist: uvicorn (>=0.38.0,<0.39.0) ; extra == "server"
Project-URL: CI/CD, https://github.com/MobileTeleSystems/syncmaster/actions
Project-URL: Documentation, https://syncmaster.readthedocs.io
Project-URL: Homepage, https://github.com/MobileTeleSystems/syncmaster
Project-URL: Source, https://github.com/MobileTeleSystems/syncmaster
Project-URL: Tracker, https://github.com/MobileTeleSystems/syncmaster/issues
